gepics.py
gepics-2025.10.3.dist-info/METADATA
gepics-2025.10.3.dist-info/WHEEL
gepics-2025.10.3.dist-info/licenses/LICENSE
gepics-2025.10.3.dist-info/RECORD
